LICENSE
MANIFEST.in
README.rst
setup.cfg
setup.py
djangostatuspage/__init__.py
djangostatuspage/admin.py
djangostatuspage/apps.py
djangostatuspage/models.py
djangostatuspage/serializers.py
djangostatuspage/signals.py
djangostatuspage/tests.py
djangostatuspage/urls.py
djangostatuspage/urls_ui.py
djangostatuspage/views.py
djangostatuspage.egg-info/PKG-INFO
djangostatuspage.egg-info/SOURCES.txt
djangostatuspage.egg-info/dependency_links.txt
djangostatuspage.egg-info/requires.txt
djangostatuspage.egg-info/top_level.txt
djangostatuspage/migrations/0001_initial.py
djangostatuspage/migrations/__init__.py
djangostatuspage/templates/djangostatuspage/base.html
djangostatuspage/templates/djangostatuspage/status_page.html